yogi/__init__.py
yogi/__init__.pyi
yogi/py.typed
yogi/yogi.pyi
yogi-1.3.1.dist-info/LICENSE
yogi-1.3.1.dist-info/METADATA
yogi-1.3.1.dist-info/WHEEL
yogi-1.3.1.dist-info/top_level.txt
yogi-1.3.1.dist-info/RECORD
