Metadata-Version: 2.1
Name: yogi
Version: 1.3.1
Summary: Simple typed interface to read input in Python
Home-page: https://github.com/jutge-org/yogi
Author: Jordi Petit
Author-email: jpetit@cs.upc.edu
License: Apache
Download-URL: https://github.com/jutge-org/yogi/tarball/1.3.1
Keywords: yogi,education,input,read,scan
Platform: UNKNOWN
Classifier: Development Status :: 5 - Production/Stable
Classifier: Environment :: Console
Classifier: Intended Audience :: Education
Classifier: License :: OSI Approved :: Apache Software License
Classifier: Operating System :: OS Independent
Classifier: Programming Language :: Python
Classifier: Topic :: Education
